genotools/__init__.py
genotools/__main__.py
genotools/ancestry.py
genotools/dependencies.py
genotools/download_refs.py
genotools/gwas.py
genotools/imputation.py
genotools/pipeline.py
genotools/qc.py
genotools/utils.py
genotools/container/Dockerfile
genotools/container/GP2_merge_APRIL_2023_ready_genotools_callrate_sex_ancestry_umap_linearsvc_ancestry_model.pkl
genotools/container/GP2_merge_release6_NOVEMBER_ready_genotools_qc_umap_linearsvc_ancestry_model.pkl
genotools/container/__init__.py
genotools/container/requirements.txt
genotools/container/run.py
the_real_genotools-1.3.6.dist-info/licenses/LICENSE
the_real_genotools-1.3.6.dist-info/METADATA
the_real_genotools-1.3.6.dist-info/WHEEL
the_real_genotools-1.3.6.dist-info/entry_points.txt
the_real_genotools-1.3.6.dist-info/top_level.txt
the_real_genotools-1.3.6.dist-info/RECORD
