Metadata-Version: 2.4
Name: the_real_genotools
Version: 1.3.6
Summary: A collection of tools for genotype quality control and analysis
Home-page: https://github.com/dvitale199/GenoTools
Author: Dan Vitale
Author-email: d.vitale199@gmail.com
License: Apache License 2.0
Classifier: Programming Language :: Python :: 3
Classifier: Operating System :: OS Independent
Requires-Python: >=3.8
License-File: LICENSE
Requires-Dist: dash_bio>=1.0.2
Requires-Dist: joblib>=1.3.0
Requires-Dist: matplotlib>=3.6.2
Requires-Dist: numba>=0.57.1
Requires-Dist: numpy>=1.23.5
Requires-Dist: pandas>=2.0.3
Requires-Dist: Pillow>=9.3.0
Requires-Dist: plotly>=5.11.0
Requires-Dist: requests>=2.28.1
Requires-Dist: scikit_learn>=1.3.0
Requires-Dist: scipy>=1.9.3
Requires-Dist: seaborn>=0.12.1
Requires-Dist: setuptools>=65.6.3
Requires-Dist: statsmodels>=0.13.5
Requires-Dist: streamlit>=1.15.2
Requires-Dist: umap_learn==0.5.3
Requires-Dist: xgboost>=1.7.6
Provides-Extra: dev
Requires-Dist: pytest>=3.7; extra == "dev"
Requires-Dist: twine>=1.11.0; extra == "dev"
Dynamic: author
Dynamic: author-email
Dynamic: classifier
Dynamic: description
Dynamic: description-content-type
Dynamic: home-page
Dynamic: license
Dynamic: license-file
Dynamic: provides-extra
Dynamic: requires-dist
Dynamic: requires-python
Dynamic: summary
